{
    "volume": "014",
    "issue": "06",
    "year": "1970",
    "month": "June",
    "id": "002/014/06",
    "toc": [
        {
            "title": "President Giri",
            "page": "0002-0002",
            "relativePageNumber": 1,
            "relativePageRange": "1-1",
            "fullText": [

            ],
            "author": [
                {
                    "name": "D. V. Gundappa",
                    "salutation": ""
                }
            ]
        },
        {
            "title": "Substances Complaint",
            "page": "0002-0002",
            "relativePageNumber": 1,
            "relativePageRange": "1-1",
            "fullText": [

            ],
            "author": [
                {
                    "name": "D. V. Gundappa",
                    "salutation": ""
                }
            ]
        },
        {
            "title": "Wasteful litigation",
            "page": "0002-0003",
            "relativePageNumber": 1,
            "relativePageRange": "1-1",
            "fullText": [

            ],
            "author": [
                {
                    "name": "D. V. Gundappa",
                    "salutation": ""
                }
            ]
        },
        {
            "title": "Story of cow",
            "page": "0003-0003",
            "relativePageNumber": 1,
            "relativePageRange": "1-1",
            "fullText": [

            ],
            "author": [
                {
                    "name": "D. V. Gundappa",
                    "salutation": ""
                }
            ]
        },
        {
            "title": "Pledges of patrits",
            "page": "0003-0004",
            "relativePageNumber": 1,
            "relativePageRange": "1-1",
            "fullText": [

            ],
            "author": [
                {
                    "name": "D. V. Gundappa",
                    "salutation": ""
                }
            ]
        },
        {
            "title": "Proclamation of emergency",
            "page": "0004-0004",
            "relativePageNumber": 1,
            "relativePageRange": "1-1",
            "fullText": [

            ],
            "author": [
                {
                    "name": "D. V. Gundappa",
                    "salutation": ""
                }
            ]
        },
        {
            "title": "Presidents duty",
            "page": "0004-0004",
            "relativePageNumber": 1,
            "relativePageRange": "1-1",
            "fullText": [

            ],
            "author": [
                {
                    "name": "D. V. Gundappa",
                    "salutation": ""
                }
            ]
        },
        {
            "title": "Repuduation of debts",
            "page": "0004-0005",
            "relativePageNumber": 1,
            "relativePageRange": "1-1",
            "fullText": [

            ],
            "author": [
                {
                    "name": "D. V. Gundappa",
                    "salutation": ""
                }
            ]
        },
        {
            "title": "Constitutuonal provisions not adequate",
            "page": "0005-0005",
            "relativePageNumber": 1,
            "relativePageRange": "1-1",
            "fullText": [

            ],
            "author": [
                {
                    "name": "D. V. Gundappa",
                    "salutation": ""
                }
            ]
        },
        {
            "title": "Parliment of law and order",
            "page": "0005-0005",
            "relativePageNumber": 1,
            "relativePageRange": "1-1",
            "fullText": [

            ],
            "author": [
                {
                    "name": "D. V. Gundappa",
                    "salutation": ""
                }
            ]
        },
        {
            "title": "Present government ineffective",
            "page": "0005-0006",
            "relativePageNumber": 1,
            "relativePageRange": "1-1",
            "fullText": [

            ],
            "author": [
                {
                    "name": "D. V. Gundappa",
                    "salutation": ""
                }
            ]
        },
        {
            "title": "Voilence, a contemprory world feature",
            "page": "0006-0006",
            "relativePageNumber": 1,
            "relativePageRange": "1-1",
            "fullText": [

            ],
            "author": [
                {
                    "name": "D. V. Gundappa",
                    "salutation": ""
                }
            ]
        },
        {
            "title": "Assert authority",
            "page": "0006-0007",
            "relativePageNumber": 1,
            "relativePageRange": "1-1",
            "fullText": [

            ],
            "author": [
                {
                    "name": "D. V. Gundappa",
                    "salutation": ""
                }
            ]
        },
        {
            "title": "Short range antidote",
            "page": "0007-0007",
            "relativePageNumber": 1,
            "relativePageRange": "1-1",
            "fullText": [

            ],
            "author": [
                {
                    "name": "D. V. Gundappa",
                    "salutation": ""
                }
            ]
        },
        {
            "title": "Danda",
            "page": "0007-0008",
            "relativePageNumber": 1,
            "relativePageRange": "1-1",
            "fullText": [

            ],
            "author": [
                {
                    "name": "D. V. Gundappa",
                    "salutation": ""
                }
            ]
        },
        {
            "title": "Three friends",
            "page": "0008-0008",
            "relativePageNumber": 1,
            "relativePageRange": "1-1",
            "fullText": [

            ],
            "author": [
                {
                    "name": "D. V. Gundappa",
                    "salutation": ""
                }
            ]
        },
        {
            "title": "Obscenity test",
            "page": "0008-0008",
            "relativePageNumber": 1,
            "relativePageRange": "1-1",
            "fullText": [

            ],
            "author": [
                {
                    "name": "D. V. Gundappa",
                    "salutation": ""
                }
            ]
        },
        {
            "title": "Will Mr. Giri act?",
            "page": "0008-0009",
            "relativePageNumber": 1,
            "relativePageRange": "1-1",
            "fullText": [

            ],
            "author": [
                {
                    "name": "D. V. Gundappa",
                    "salutation": ""
                }
            ]
        },
        {
            "title": "Dairy for May70",
            "page": "0009-0010",
            "relativePageNumber": 1,
            "relativePageRange": "1-1",
            "fullText": [

            ],
            "author": [
                {
                    "name": "Editor",
                    "salutation": ""
                }
            ]
        },
        {
            "title": "Economic approach to a political problem: Bengal Report",
            "page": "0010-0012",
            "relativePageNumber": 1,
            "relativePageRange": "1-1",
            "fullText": [

            ],
            "author": [
                {
                    "name": "Mr. K. K sinha",
                    "salutation": ""
                }
            ]
        },
        {
            "title": "Tax component in the prices of various commodities",
            "page": "0012-0024",
            "relativePageNumber": 1,
            "relativePageRange": "1-1",
            "fullText": [

            ],
            "author": [
                {
                    "name": "Dr. R. C Cooper",
                    "salutation": ""
                }
            ]
        },
        {
            "title": "The students mistresses",
            "page": "0024-0025",
            "relativePageNumber": 1,
            "relativePageRange": "1-1",
            "fullText": [

            ],
            "author": [
                {
                    "name": "Editor",
                    "salutation": ""
                }
            ]
        },
        {
            "title": "Dairy for April 1970",
            "page": "0025-0025",
            "relativePageNumber": 1,
            "relativePageRange": "1-1",
            "fullText": [

            ],
            "author": [
                {
                    "name": "Editor",
                    "salutation": ""
                }
            ]
        }
    ]
}